ruhrohrotaryio.py
circuitpython_ruhrohrotaryio-1.0.dist-info/LICENSE
circuitpython_ruhrohrotaryio-1.0.dist-info/METADATA
circuitpython_ruhrohrotaryio-1.0.dist-info/WHEEL
circuitpython_ruhrohrotaryio-1.0.dist-info/top_level.txt
circuitpython_ruhrohrotaryio-1.0.dist-info/RECORD
