Metadata-Version: 2.1
Name: circuitpython-ruhrohrotaryio
Version: 1.0
Summary: pretend to be 'rotaryio' for boards that need non-sequential pins
Author-email: Tod Kurt <tod@todbot.com>
License: MIT
Project-URL: Homepage, https://github.com/todbot/CircuitPython_RuhRohRotaryIO
Keywords: adafruit,blinka,circuitpython,micropython,ruhrohrotaryio,rotaryio,rotaryencoder,rotary,encoder,incrementalecoder
Classifier: Intended Audience :: Developers
Classifier: Topic :: Software Development :: Libraries
Classifier: Topic :: Software Development :: Embedded Systems
Classifier: Topic :: System :: Hardware
Classifier: License :: OSI Approved :: MIT License
Classifier: Programming Language :: Python :: 3
License-File: LICENSE
Requires-Dist: Adafruit-Blinka
Provides-Extra: optional
